LICENSE
MANIFEST.in
README.rst
setup.cfg
setup.py
address_formatter/__init__.py
address_formatter/address.py
address_formatter.egg-info/PKG-INFO
address_formatter.egg-info/SOURCES.txt
address_formatter.egg-info/dependency_links.txt
address_formatter.egg-info/requires.txt
address_formatter.egg-info/top_level.txt